bamaligncleaner/__init__.py
bamaligncleaner/cli.py
bamaligncleaner/main.py
bamaligncleaner-0.4.dist-info/licenses/LICENSE
bamaligncleaner-0.4.dist-info/METADATA
bamaligncleaner-0.4.dist-info/WHEEL
bamaligncleaner-0.4.dist-info/entry_points.txt
bamaligncleaner-0.4.dist-info/top_level.txt
bamaligncleaner-0.4.dist-info/RECORD
