Metadata-Version: 2.4
Name: bamAlignCleaner
Version: 0.4
Summary: Removes unaligned references in BAM alignment file
Home-page: https://github.com/maxibor/bamAlignCleaner
License: MIT
Requires-Python: >=3.6
License-File: LICENSE
Requires-Dist: pysam
Requires-Dist: tqdm
Requires-Dist: click
Dynamic: description
Dynamic: description-content-type
Dynamic: home-page
Dynamic: license
Dynamic: license-file
Dynamic: requires-dist
Dynamic: requires-python
Dynamic: summary
